waizao/__init__.py
waizao/api_demo.py
waizao/export_tool.py
waizao/api/__init__.py
waizao/api/spider_api.py
waizao/api/stock_api.py
waizao-1.1.3.dist-info/LICENSE
waizao-1.1.3.dist-info/METADATA
waizao-1.1.3.dist-info/WHEEL
waizao-1.1.3.dist-info/top_level.txt
waizao-1.1.3.dist-info/RECORD
